django_widgy-0.9.1.data/data/bin/daisydiff/LICENSE.txt
django_widgy-0.9.1.data/data/bin/daisydiff/NOTICE.txt
django_widgy-0.9.1.data/data/bin/daisydiff/README.txt
django_widgy-0.9.1.data/data/bin/daisydiff/daisydiff.jar
widgy/__init__.py
widgy/admin.py
widgy/cats.py
widgy/exceptions.py
widgy/forms.py
widgy/middleware.py
widgy/signals.py
widgy/site.py
widgy/utils.py
widgy/widgets.py
widgy/contrib/__init__.py
widgy/contrib/form_builder/__init__.py
widgy/contrib/form_builder/admin.py
widgy/contrib/form_builder/forms.py
widgy/contrib/form_builder/models.py
widgy/contrib/form_builder/tests.py
widgy/contrib/form_builder/views.py
widgy/contrib/form_builder/migrations/0001_initial.py
widgy/contrib/form_builder/migrations/0002_auto_20150311_2118.py
widgy/contrib/form_builder/migrations/0003_auto_20150730_1401.py
widgy/contrib/form_builder/migrations/0004_auto_20171117_2056.py
widgy/contrib/form_builder/migrations/0005_auto_20180425_2149.py
widgy/contrib/form_builder/migrations/__init__.py
widgy/contrib/form_builder/static/widgy/form_builder/admin.scss
widgy/contrib/form_builder/static/widgy/form_builder/forminput.js
widgy/contrib/form_builder/static/widgy/form_builder/forminput.scss
widgy/contrib/form_builder/templates/admin/form_builder/form/change_form.html
widgy/contrib/form_builder/templates/widgy/form_builder/form_email.html
widgy/contrib/form_builder/templates/widgy/form_builder/form/preview.html
widgy/contrib/form_builder/templates/widgy/form_builder/form/render.html
widgy/contrib/form_builder/templates/widgy/form_builder/formfield/render.html
widgy/contrib/form_builder/templates/widgy/form_builder/forminput/render.html
widgy/contrib/form_builder/templates/widgy/form_builder/submitbutton/render.html
widgy/contrib/form_builder/templates/widgy/form_builder/uncaptcha/render.html
widgy/contrib/page_builder/__init__.py
widgy/contrib/page_builder/admin.py
widgy/contrib/page_builder/models.py
widgy/contrib/page_builder/tests.py
widgy/contrib/page_builder/db/__init__.py
django_widgy-0.9.1.dist-info/LICENSE
django_widgy-0.9.1.dist-info/METADATA
django_widgy-0.9.1.dist-info/WHEEL
django_widgy-0.9.1.dist-info/top_level.txt
django_widgy-0.9.1.dist-info/RECORD
