Metadata-Version: 2.1
Name: django-widgy
Version: 0.9.1
Summary: A CMS framework for Django built on a heterogenous tree editor.
Home-page: http://docs.wid.gy/
Author: Fusionbox, Inc.
Author-email: programmers@fusionbox.com
License: UNKNOWN
Platform: UNKNOWN
Classifier: Development Status :: 4 - Beta
Classifier: Environment :: Web Environment
Classifier: Framework :: Django
Classifier: Intended Audience :: Developers
Classifier: License :: OSI Approved :: Apache Software License
Classifier: Topic :: Internet :: WWW/HTTP :: Dynamic Content
Classifier: Topic :: Internet :: WWW/HTTP :: Site Management
Classifier: Natural Language :: English
Classifier: Programming Language :: JavaScript
Classifier: Programming Language :: Python
Classifier: Programming Language :: Python :: 2.6
Classifier: Programming Language :: Python :: 2.7
License-File: LICENSE
Requires-Dist: django-treebeard
Requires-Dist: django-pyscss (>=2.0.0)
Requires-Dist: six
Requires-Dist: django-compressor (>=1.3)
Requires-Dist: beautifulsoup4
Requires-Dist: django-argonauts (>=1.1.4)
Requires-Dist: Django (>=1.11)
Requires-Dist: html5lib
Requires-Dist: markdown
Provides-Extra: all
Requires-Dist: phonenumbers (>=5) ; extra == 'all'
Requires-Dist: sorl-thumbnail (>=11.12) ; extra == 'all'
Requires-Dist: django-extensions ; extra == 'all'
Requires-Dist: html2text (>=3.200.3) ; extra == 'all'
Requires-Dist: markdown ; extra == 'all'
Requires-Dist: django-filer (>=0.9.10) ; extra == 'all'
Requires-Dist: bleach ; extra == 'all'
Requires-Dist: mezzanine (>=4.0.0) ; extra == 'all'
Provides-Extra: form_builder
Requires-Dist: django-extensions ; extra == 'form_builder'
Requires-Dist: html2text (>=3.200.3) ; extra == 'form_builder'
Requires-Dist: phonenumbers (>=5) ; extra == 'form_builder'
Provides-Extra: page_builder
Requires-Dist: django-filer (>=0.9.10) ; extra == 'page_builder'
Requires-Dist: markdown ; extra == 'page_builder'
Requires-Dist: bleach ; extra == 'page_builder'
Requires-Dist: sorl-thumbnail (>=11.12) ; extra == 'page_builder'
Provides-Extra: widgy_mezzanine
Requires-Dist: mezzanine (>=4.0.0) ; extra == 'widgy_mezzanine'
